{
	"name": "subscriber",
	"type": "flogo:trigger",
	"version": "0.0.1",
	"title": "Apache Pulsar Subscriber",
	"description": "A simple pulsar subscriber which reads messages from apache pulsar queue",
	"settings": [
		{
			"name": "connection",
			"type": "connection",
			"allowed": null,
			"required": true
		}
	],
	"output": [
		{
			"name": "message",
			"type": "string",
			"allowed": null,
			"required": false
		}
	],
	"handler": {
		"settings": [
			{
				"name": "topic",
				"type": "string",
				"allowed": null,
				"required": true,
				"value":"/tenant/namespace/topic"
			},
			{
				"name": "subscription",
				"type": "string",
				"allowed": null,
				"required": true,
				"value":""
			}
		]
	}
}
